helpfulFiles/buildModule.py
helpfulFiles/mainDistribute.py
src/galaxy_encrytion/__init__.py
src/galaxy_encrytion/galaxyEncryption.py
galaxypersonallib-0.0.2.dist-info/METADATA
galaxypersonallib-0.0.2.dist-info/WHEEL
galaxypersonallib-0.0.2.dist-info/licenses/LICENSE
galaxypersonallib-0.0.2.dist-info/RECORD
